README.md
nowgg.py
setup.py
nowgg.egg-info/PKG-INFO
nowgg.egg-info/SOURCES.txt
nowgg.egg-info/dependency_links.txt
nowgg.egg-info/entry_points.txt
nowgg.egg-info/requires.txt
nowgg.egg-info/top_level.txt