Metadata-Version: 2.1
Name: nowgg
Version: 1.1.4
Summary: UNKNOWN
Home-page: UNKNOWN
Author-email: cloudmaster@now.gg
License: UNKNOWN
Platform: UNKNOWN
